css_resolver/__init__.py
css_resolver/resolver.py
test_css_resolver/__init__.py
test_css_resolver/test_resolver.py
css_resolver-0.0.1.dist-info/LICENSE
css_resolver-0.0.1.dist-info/METADATA
css_resolver-0.0.1.dist-info/WHEEL
css_resolver-0.0.1.dist-info/top_level.txt
css_resolver-0.0.1.dist-info/RECORD
