Metadata-Version: 2.1
Name: css-resolver
Version: 0.0.1
License-File: LICENSE
Requires-Dist: requests
Requires-Dist: argparse
Requires-Dist: colorama
Requires-Dist: beautifulsoup4
